MANIFEST.in
setup.py
pbs_account_consumer/__init__.py
pbs_account_consumer/admin.py
pbs_account_consumer/auth.py
pbs_account_consumer/constants.py
pbs_account_consumer/context_processors.py
pbs_account_consumer/forms.py
pbs_account_consumer/models.py
pbs_account_consumer/settings.py
pbs_account_consumer/store.py
pbs_account_consumer/urls.py
pbs_account_consumer/views.py
pbs_account_consumer.egg-info/PKG-INFO
pbs_account_consumer.egg-info/SOURCES.txt
pbs_account_consumer.egg-info/dependency_links.txt
pbs_account_consumer.egg-info/not-zip-safe
pbs_account_consumer.egg-info/requires.txt
pbs_account_consumer.egg-info/top_level.txt
pbs_account_consumer/migrations/0001_initial.py
pbs_account_consumer/migrations/__init__.py
pbs_account_consumer/templates/admin/openid.login.html
pbs_account_consumer/templates/openid/response.html
pbs_account_consumer/templates/openid/setup_needed.html
pbs_account_consumer/templates/registration/change_password.html
pbs_account_consumer/templates/registration/login.html
test_project/tests/__init__.py
test_project/tests/tests.py