Metadata-Version: 1.0
Name: pbs-account-consumer
Version: 1.5.0
Summary: PBS Account Consumer
Home-page: UNKNOWN
Author: PBS Core Services Team
Author-email: PBSi-Team-Core-Services@pbs.org
License: UNKNOWN
Platform: UNKNOWN
